pydda/__init__.py
pydda/constraints/__init__.py
pydda/constraints/model_data.py
pydda/constraints/station_data.py
pydda/cost_functions/__init__.py
pydda/cost_functions/_cost_functions_auglag.py
pydda/cost_functions/_cost_functions_jax.py
pydda/cost_functions/_cost_functions_numpy.py
pydda/cost_functions/_cost_functions_tensorflow.py
pydda/cost_functions/cost_functions.py
pydda/initialization/__init__.py
pydda/initialization/wind_fields.py
pydda/io/__init__.py
pydda/io/read_grid.py
pydda/retrieval/__init__.py
pydda/retrieval/angles.py
pydda/retrieval/auglag.py
pydda/retrieval/nesting.py
pydda/retrieval/wind_retrieve.py
pydda/tests/__init__.py
pydda/tests/procedures.py
pydda/tests/sample_files.py
pydda/tests/test_cost_functions.py
pydda/tests/test_era5.py
pydda/tests/test_initialization.py
pydda/tests/test_plots.py
pydda/tests/test_retrieval.py
pydda/tests/data/test_era5.nc
pydda/vis/__init__.py
pydda/vis/barb_plot.py
pydda/vis/quiver_plot.py
pydda/vis/streamline_plot.py
pydda-2.2.0.dist-info/licenses/LICENSE
pydda-2.2.0.dist-info/METADATA
pydda-2.2.0.dist-info/WHEEL
pydda-2.2.0.dist-info/top_level.txt
pydda-2.2.0.dist-info/RECORD
