Metadata-Version: 2.4
Name: pydda
Version: 2.2.0
Summary: Py-DDA
Home-page: https://openradarscience.org/PyDDA
Author: Bobby Jackson
Author-email: rjackson@anl.gov
License: BSD
Project-URL: Bug Reports, https://github.com/openradar/PyDDA/issues
Project-URL: Source, https://github.com/openradar/PyDDA
Platform: Linux
Platform: Windows
Platform: OSX
License-File: LICENSE
Requires-Dist: matplotlib
Requires-Dist: cartopy>=0.16.0
Requires-Dist: arm_pyart
Requires-Dist: dask
Requires-Dist: distributed
Requires-Dist: scipy
Requires-Dist: numpy
Dynamic: author
Dynamic: author-email
Dynamic: description
Dynamic: description-content-type
Dynamic: home-page
Dynamic: license
Dynamic: license-file
Dynamic: platform
Dynamic: project-url
Dynamic: requires-dist
Dynamic: summary
